README.md
pyproject.toml
pulumi_synced_folder/__init__.py
pulumi_synced_folder/_utilities.py
pulumi_synced_folder/azure_blob_folder.py
pulumi_synced_folder/google_cloud_folder.py
pulumi_synced_folder/provider.py
pulumi_synced_folder/pulumi-plugin.json
pulumi_synced_folder/py.typed
pulumi_synced_folder/s3_bucket_folder.py
pulumi_synced_folder.egg-info/PKG-INFO
pulumi_synced_folder.egg-info/SOURCES.txt
pulumi_synced_folder.egg-info/dependency_links.txt
pulumi_synced_folder.egg-info/requires.txt
pulumi_synced_folder.egg-info/top_level.txt