Metadata-Version: 2.4
Name: pulumi_synced_folder
Version: 0.12.4
Summary: A Pulumi component that synchronizes a local folder to Amazon S3, Azure Blob Storage, or Google Cloud Storage.
Project-URL: Homepage, https://pulumi.com
Project-URL: Repository, https://github.com/pulumi/pulumi-synced-folder
Keywords: pulumi,aws,azure,gcp,category/cloud,kind/component
Requires-Python: >=3.9
Requires-Dist: parver>=0.2.1
Requires-Dist: pulumi<4.0.0,>=3.0.0
Requires-Dist: semver>=2.8.1
Requires-Dist: typing-extensions<5,>=4.11; python_version < "3.11"
